{
  "sections": {
    "main": {
      "type": "article",
      "blocks": {
        "related-products": {
          "type": "related",
          "settings": {
            "title": "Related products"
          }
        },
        "recent-articles": {
          "type": "recent",
          "settings": {
            "title": "Recent articles"
          }
        }
      },
      "block_order": [
        "related-products",
        "recent-articles"
      ],
      "settings": {
        "show_image": true,
        "show_date": true,
        "show_author": true,
        "tags": false,
        "show_sharing": true,
        "arrows": false,
        "height": "four-fifty-height-hero",
        "mobile_height": "screen-height-one-third--mobile",
        "padding_top": 0,
        "padding_bottom": 50
      }
    }
  },
  "order": [
    "main"
  ]
}